[
  {
    "version": "1.8",
    "sites": 0,
    "php": []
  },
  {
    "version": "1.9",
    "sites": 351,
    "php": [
      {
        "version": "5.6",
        "sites": 4
      },
      {
        "version": "5.4",
        "sites": 5
      },
      {
        "version": "5.3",
        "sites": 4
      },
      {
        "version": "5.2",
        "sites": 11
      },
      {
        "version": "5.1",
        "sites": 17
      },
      {
        "version": "4.4",
        "sites": 267
      }
    ]
  },
  {
    "version": "2.0",
    "sites": 433,
    "php": [
      {
        "version": "5.6",
        "sites": 2
      },
      {
        "version": "5.4",
        "sites": 6
      },
      {
        "version": "5.3",
        "sites": 1
      },
      {
        "version": "5.2",
        "sites": 12
      },
      {
        "version": "5.1",
        "sites": 37
      },
      {
        "version": "4.4",
        "sites": 337
      }
    ]
  },
  {
    "version": "2.1",
    "sites": 768,
    "php": [
      {
        "version": "7.4",
        "sites": 1
      },
      {
        "version": "5.6",
        "sites": 18
      },
      {
        "version": "5.5",
        "sites": 3
      },
      {
        "version": "5.4",
        "sites": 39
      },
      {
        "version": "5.3",
        "sites": 13
      },
      {
        "version": "5.2",
        "sites": 20
      },
      {
        "version": "5.1",
        "sites": 172
      },
      {
        "version": "4.4",
        "sites": 394
      }
    ]
  },
  {
    "version": "3.0",
    "sites": 789,
    "php": [
      {
        "version": "8.0",
        "sites": 1
      },
      {
        "version": "7.4",
        "sites": 1
      },
      {
        "version": "7.3",
        "sites": 1
      },
      {
        "version": "5.6",
        "sites": 91
      },
      {
        "version": "5.5",
        "sites": 12
      },
      {
        "version": "5.4",
        "sites": 42
      },
      {
        "version": "5.3",
        "sites": 11
      },
      {
        "version": "5.2",
        "sites": 18
      },
      {
        "version": "5.1",
        "sites": 330
      },
      {
        "version": "4.4",
        "sites": 12
      }
    ]
  },
  {
    "version": "3.1",
    "sites": 384,
    "php": [
      {
        "version": "7.4",
        "sites": 28
      },
      {
        "version": "7.3",
        "sites": 10
      },
      {
        "version": "7.2",
        "sites": 2
      },
      {
        "version": "7.1",
        "sites": 3
      },
      {
        "version": "7.0",
        "sites": 22
      },
      {
        "version": "5.6",
        "sites": 76
      },
      {
        "version": "5.5",
        "sites": 4
      },
      {
        "version": "5.4",
        "sites": 17
      },
      {
        "version": "5.3",
        "sites": 13
      },
      {
        "version": "5.2",
        "sites": 3
      },
      {
        "version": "5.1",
        "sites": 12
      },
      {
        "version": "4.4",
        "sites": 6
      }
    ]
  },
  {
    "version": "3.2",
    "sites": 1692,
    "php": [
      {
        "version": "8.2",
        "sites": 2
      },
      {
        "version": "8.1",
        "sites": 1
      },
      {
        "version": "8.0",
        "sites": 2
      },
      {
        "version": "7.4",
        "sites": 323
      },
      {
        "version": "7.3",
        "sites": 63
      },
      {
        "version": "7.2",
        "sites": 110
      },
      {
        "version": "7.1",
        "sites": 27
      },
      {
        "version": "7.0",
        "sites": 33
      },
      {
        "version": "5.6",
        "sites": 263
      },
      {
        "version": "5.5",
        "sites": 225
      },
      {
        "version": "5.4",
        "sites": 24
      },
      {
        "version": "5.3",
        "sites": 3
      },
      {
        "version": "4.4",
        "sites": 4
      }
    ]
  },
  {
    "version": "3.3",
    "sites": 3,
    "php": [
      {
        "version": "7.3",
        "sites": 1
      },
      {
        "version": "5.6",
        "sites": 1
      }
    ]
  },
  {
    "version": "4.0",
    "sites": 122,
    "php": [
      {
        "version": "8.2",
        "sites": 9
      },
      {
        "version": "8.1",
        "sites": 1
      },
      {
        "version": "8.0",
        "sites": 5
      },
      {
        "version": "7.4",
        "sites": 25
      },
      {
        "version": "7.3",
        "sites": 19
      },
      {
        "version": "4.4",
        "sites": 1
      }
    ]
  },
  {
    "version": "4.1",
    "sites": 820,
    "php": [
      {
        "version": "8.2",
        "sites": 6
      },
      {
        "version": "8.1",
        "sites": 69
      },
      {
        "version": "8.0",
        "sites": 36
      },
      {
        "version": "7.4",
        "sites": 43
      }
    ]
  },
  {
    "version": "4.2",
    "sites": 1523,
    "php": [
      {
        "version": "8.3",
        "sites": 12
      },
      {
        "version": "8.2",
        "sites": 151
      },
      {
        "version": "8.1",
        "sites": 152
      },
      {
        "version": "8.0",
        "sites": 48
      },
      {
        "version": "7.4",
        "sites": 192
      }
    ]
  },
  {
    "version": "4.3",
    "sites": 134,
    "php": [
      {
        "version": "8.3",
        "sites": 6
      },
      {
        "version": "8.2",
        "sites": 8
      },
      {
        "version": "8.1",
        "sites": 10
      },
      {
        "version": "8.0",
        "sites": 5
      },
      {
        "version": "7.4",
        "sites": 24
      }
    ]
  },
  {
    "version": "4.4",
    "sites": 0,
    "php": []
  },
  {
    "version": "5.0",
    "sites": 0,
    "php": []
  }
]
