[
  {
    "version": "4.4",
    "sites": 730,
    "spip": [
      {
        "version": "1.9",
        "sites": 185
      },
      {
        "version": "2.0",
        "sites": 237
      },
      {
        "version": "2.1",
        "sites": 308
      }
    ]
  },
  {
    "version": "5.1",
    "sites": 613,
    "spip": [
      {
        "version": "1.9",
        "sites": 27
      },
      {
        "version": "2.0",
        "sites": 56
      },
      {
        "version": "2.1",
        "sites": 198
      },
      {
        "version": "3.0",
        "sites": 327
      },
      {
        "version": "3.1",
        "sites": 5
      }
    ]
  },
  {
    "version": "5.2",
    "sites": 111,
    "spip": [
      {
        "version": "1.9",
        "sites": 16
      },
      {
        "version": "2.0",
        "sites": 13
      },
      {
        "version": "2.1",
        "sites": 46
      },
      {
        "version": "3.0",
        "sites": 30
      },
      {
        "version": "3.1",
        "sites": 6
      }
    ]
  },
  {
    "version": "5.3",
    "sites": 125,
    "spip": [
      {
        "version": "1.9",
        "sites": 12
      },
      {
        "version": "2.0",
        "sites": 7
      },
      {
        "version": "2.1",
        "sites": 31
      },
      {
        "version": "3.0",
        "sites": 56
      },
      {
        "version": "3.1",
        "sites": 15
      },
      {
        "version": "3.2",
        "sites": 4
      }
    ]
  },
  {
    "version": "5.4",
    "sites": 338,
    "spip": [
      {
        "version": "1.9",
        "sites": 3
      },
      {
        "version": "2.0",
        "sites": 6
      },
      {
        "version": "2.1",
        "sites": 74
      },
      {
        "version": "3.0",
        "sites": 64
      },
      {
        "version": "3.1",
        "sites": 27
      },
      {
        "version": "3.2",
        "sites": 164
      }
    ]
  },
  {
    "version": "5.5",
    "sites": 37,
    "spip": [
      {
        "version": "1.9",
        "sites": 1
      },
      {
        "version": "2.1",
        "sites": 6
      },
      {
        "version": "3.0",
        "sites": 11
      },
      {
        "version": "3.1",
        "sites": 5
      },
      {
        "version": "3.2",
        "sites": 14
      }
    ]
  },
  {
    "version": "5.6",
    "sites": 758,
    "spip": [
      {
        "version": "1.9",
        "sites": 3
      },
      {
        "version": "2.0",
        "sites": 9
      },
      {
        "version": "2.1",
        "sites": 35
      },
      {
        "version": "3.0",
        "sites": 360
      },
      {
        "version": "3.1",
        "sites": 125
      },
      {
        "version": "3.2",
        "sites": 226
      }
    ]
  },
  {
    "version": "7.0",
    "sites": 56,
    "spip": [
      {
        "version": "3.0",
        "sites": 1
      },
      {
        "version": "3.1",
        "sites": 10
      },
      {
        "version": "3.2",
        "sites": 45
      }
    ]
  },
  {
    "version": "7.1",
    "sites": 102,
    "spip": [
      {
        "version": "3.1",
        "sites": 8
      },
      {
        "version": "3.2",
        "sites": 94
      }
    ]
  },
  {
    "version": "7.2",
    "sites": 96,
    "spip": [
      {
        "version": "3.1",
        "sites": 5
      },
      {
        "version": "3.2",
        "sites": 90
      },
      {
        "version": "3.3",
        "sites": 1
      }
    ]
  },
  {
    "version": "7.3",
    "sites": 182,
    "spip": [
      {
        "version": "3.1",
        "sites": 23
      },
      {
        "version": "3.2",
        "sites": 131
      },
      {
        "version": "3.3",
        "sites": 6
      },
      {
        "version": "4.0",
        "sites": 22
      }
    ]
  },
  {
    "version": "7.4",
    "sites": 152,
    "spip": [
      {
        "version": "3.0",
        "sites": 1
      },
      {
        "version": "3.1",
        "sites": 8
      },
      {
        "version": "3.2",
        "sites": 112
      },
      {
        "version": "3.3",
        "sites": 1
      },
      {
        "version": "4.0",
        "sites": 30
      }
    ]
  },
  {
    "version": "8.0",
    "sites": 7,
    "spip": [
      {
        "version": "4.0",
        "sites": 7
      }
    ]
  }
]
