[
  {
    "version": "1.9",
    "sites": 500,
    "php": [
      {
        "version": "5.6",
        "sites": 5
      },
      {
        "version": "5.5",
        "sites": 2
      },
      {
        "version": "5.4",
        "sites": 7
      },
      {
        "version": "5.3",
        "sites": 21
      },
      {
        "version": "5.2",
        "sites": 22
      },
      {
        "version": "5.1",
        "sites": 29
      },
      {
        "version": "4.4",
        "sites": 343
      }
    ]
  },
  {
    "version": "2.0",
    "sites": 666,
    "php": [
      {
        "version": "5.6",
        "sites": 17
      },
      {
        "version": "5.5",
        "sites": 1
      },
      {
        "version": "5.4",
        "sites": 11
      },
      {
        "version": "5.3",
        "sites": 13
      },
      {
        "version": "5.2",
        "sites": 23
      },
      {
        "version": "5.1",
        "sites": 71
      },
      {
        "version": "4.4",
        "sites": 450
      }
    ]
  },
  {
    "version": "2.1",
    "sites": 1407,
    "php": [
      {
        "version": "7.4",
        "sites": 3
      },
      {
        "version": "7.3",
        "sites": 3
      },
      {
        "version": "7.2",
        "sites": 1
      },
      {
        "version": "7.0",
        "sites": 1
      },
      {
        "version": "5.6",
        "sites": 61
      },
      {
        "version": "5.5",
        "sites": 14
      },
      {
        "version": "5.4",
        "sites": 100
      },
      {
        "version": "5.3",
        "sites": 71
      },
      {
        "version": "5.2",
        "sites": 105
      },
      {
        "version": "5.1",
        "sites": 241
      },
      {
        "version": "4.4",
        "sites": 579
      }
    ]
  },
  {
    "version": "3.0",
    "sites": 1846,
    "php": [
      {
        "version": "7.4",
        "sites": 4
      },
      {
        "version": "7.3",
        "sites": 3
      },
      {
        "version": "7.2",
        "sites": 1
      },
      {
        "version": "7.0",
        "sites": 1
      },
      {
        "version": "5.6",
        "sites": 461
      },
      {
        "version": "5.5",
        "sites": 41
      },
      {
        "version": "5.4",
        "sites": 169
      },
      {
        "version": "5.3",
        "sites": 124
      },
      {
        "version": "5.2",
        "sites": 75
      },
      {
        "version": "5.1",
        "sites": 381
      }
    ]
  },
  {
    "version": "3.1",
    "sites": 1088,
    "php": [
      {
        "version": "7.4",
        "sites": 8
      },
      {
        "version": "7.3",
        "sites": 58
      },
      {
        "version": "7.2",
        "sites": 34
      },
      {
        "version": "7.1",
        "sites": 26
      },
      {
        "version": "7.0",
        "sites": 61
      },
      {
        "version": "5.6",
        "sites": 320
      },
      {
        "version": "5.5",
        "sites": 29
      },
      {
        "version": "5.4",
        "sites": 57
      },
      {
        "version": "5.3",
        "sites": 45
      },
      {
        "version": "5.2",
        "sites": 18
      },
      {
        "version": "5.1",
        "sites": 5
      }
    ]
  },
  {
    "version": "3.2",
    "sites": 2759,
    "php": [
      {
        "version": "7.4",
        "sites": 71
      },
      {
        "version": "7.3",
        "sites": 280
      },
      {
        "version": "7.2",
        "sites": 348
      },
      {
        "version": "7.1",
        "sites": 174
      },
      {
        "version": "7.0",
        "sites": 112
      },
      {
        "version": "5.6",
        "sites": 337
      },
      {
        "version": "5.5",
        "sites": 30
      },
      {
        "version": "5.4",
        "sites": 204
      },
      {
        "version": "5.3",
        "sites": 19
      }
    ]
  },
  {
    "version": "3.3",
    "sites": 78,
    "php": [
      {
        "version": "7.4",
        "sites": 5
      },
      {
        "version": "7.3",
        "sites": 10
      },
      {
        "version": "7.2",
        "sites": 11
      },
      {
        "version": "7.1",
        "sites": 1
      },
      {
        "version": "7.0",
        "sites": 2
      },
      {
        "version": "5.6",
        "sites": 1
      }
    ]
  }
]
