[
  {
    "version": "1.8",
    "sites": 0,
    "php": []
  },
  {
    "version": "1.9",
    "sites": 25,
    "php": [
      {
        "version": "5.4",
        "sites": 2
      },
      {
        "version": "5.3",
        "sites": 1
      },
      {
        "version": "5.2",
        "sites": 4
      }
    ]
  },
  {
    "version": "2.0",
    "sites": 23,
    "php": [
      {
        "version": "5.6",
        "sites": 2
      },
      {
        "version": "5.4",
        "sites": 2
      },
      {
        "version": "5.2",
        "sites": 5
      }
    ]
  },
  {
    "version": "2.1",
    "sites": 88,
    "php": [
      {
        "version": "5.6",
        "sites": 6
      },
      {
        "version": "5.5",
        "sites": 2
      },
      {
        "version": "5.4",
        "sites": 9
      },
      {
        "version": "5.3",
        "sites": 11
      },
      {
        "version": "5.2",
        "sites": 5
      },
      {
        "version": "4.4",
        "sites": 1
      }
    ]
  },
  {
    "version": "3.0",
    "sites": 149,
    "php": [
      {
        "version": "7.4",
        "sites": 1
      },
      {
        "version": "7.3",
        "sites": 1
      },
      {
        "version": "5.6",
        "sites": 30
      },
      {
        "version": "5.5",
        "sites": 8
      },
      {
        "version": "5.4",
        "sites": 30
      },
      {
        "version": "5.3",
        "sites": 7
      },
      {
        "version": "5.2",
        "sites": 4
      }
    ]
  },
  {
    "version": "3.1",
    "sites": 152,
    "php": [
      {
        "version": "7.4",
        "sites": 15
      },
      {
        "version": "7.3",
        "sites": 7
      },
      {
        "version": "7.1",
        "sites": 1
      },
      {
        "version": "7.0",
        "sites": 11
      },
      {
        "version": "5.6",
        "sites": 31
      },
      {
        "version": "5.5",
        "sites": 1
      },
      {
        "version": "5.4",
        "sites": 7
      },
      {
        "version": "5.3",
        "sites": 13
      },
      {
        "version": "5.2",
        "sites": 1
      }
    ]
  },
  {
    "version": "3.2",
    "sites": 708,
    "php": [
      {
        "version": "7.4",
        "sites": 106
      },
      {
        "version": "7.3",
        "sites": 40
      },
      {
        "version": "7.2",
        "sites": 29
      },
      {
        "version": "7.1",
        "sites": 15
      },
      {
        "version": "7.0",
        "sites": 21
      },
      {
        "version": "5.6",
        "sites": 127
      },
      {
        "version": "5.5",
        "sites": 87
      },
      {
        "version": "5.4",
        "sites": 10
      },
      {
        "version": "5.3",
        "sites": 2
      }
    ]
  },
  {
    "version": "3.3",
    "sites": 0,
    "php": []
  },
  {
    "version": "4.0",
    "sites": 30,
    "php": [
      {
        "version": "8.0",
        "sites": 3
      },
      {
        "version": "7.4",
        "sites": 5
      },
      {
        "version": "7.3",
        "sites": 5
      }
    ]
  },
  {
    "version": "4.1",
    "sites": 590,
    "php": [
      {
        "version": "8.4",
        "sites": 1
      },
      {
        "version": "8.3",
        "sites": 2
      },
      {
        "version": "8.1",
        "sites": 9
      },
      {
        "version": "8.0",
        "sites": 5
      },
      {
        "version": "7.4",
        "sites": 9
      }
    ]
  },
  {
    "version": "4.2",
    "sites": 145,
    "php": [
      {
        "version": "8.3",
        "sites": 2
      },
      {
        "version": "8.2",
        "sites": 7
      },
      {
        "version": "8.1",
        "sites": 20
      },
      {
        "version": "8.0",
        "sites": 7
      },
      {
        "version": "7.4",
        "sites": 16
      }
    ]
  },
  {
    "version": "4.3",
    "sites": 242,
    "php": [
      {
        "version": "8.4",
        "sites": 5
      },
      {
        "version": "8.3",
        "sites": 35
      },
      {
        "version": "8.2",
        "sites": 22
      },
      {
        "version": "8.1",
        "sites": 11
      },
      {
        "version": "8.0",
        "sites": 7
      },
      {
        "version": "7.4",
        "sites": 19
      }
    ]
  },
  {
    "version": "4.4",
    "sites": 1609,
    "php": [
      {
        "version": "8.4",
        "sites": 64
      },
      {
        "version": "8.3",
        "sites": 243
      },
      {
        "version": "8.2",
        "sites": 130
      },
      {
        "version": "8.1",
        "sites": 96
      },
      {
        "version": "8.0",
        "sites": 19
      },
      {
        "version": "7.4",
        "sites": 64
      }
    ]
  },
  {
    "version": "5.0",
    "sites": 0,
    "php": []
  }
]
