[
  {
    "version": "4.4",
    "sites": 1291,
    "spip": [
      {
        "version": "1.9",
        "sites": 328
      },
      {
        "version": "2.0",
        "sites": 419
      },
      {
        "version": "2.1",
        "sites": 544
      }
    ]
  },
  {
    "version": "5.1",
    "sites": 678,
    "spip": [
      {
        "version": "1.9",
        "sites": 29
      },
      {
        "version": "2.0",
        "sites": 67
      },
      {
        "version": "2.1",
        "sites": 222
      },
      {
        "version": "3.0",
        "sites": 355
      },
      {
        "version": "3.1",
        "sites": 5
      }
    ]
  },
  {
    "version": "5.2",
    "sites": 172,
    "spip": [
      {
        "version": "1.9",
        "sites": 19
      },
      {
        "version": "2.0",
        "sites": 16
      },
      {
        "version": "2.1",
        "sites": 72
      },
      {
        "version": "3.0",
        "sites": 49
      },
      {
        "version": "3.1",
        "sites": 16
      }
    ]
  },
  {
    "version": "5.3",
    "sites": 239,
    "spip": [
      {
        "version": "1.9",
        "sites": 18
      },
      {
        "version": "2.0",
        "sites": 11
      },
      {
        "version": "2.1",
        "sites": 62
      },
      {
        "version": "3.0",
        "sites": 100
      },
      {
        "version": "3.1",
        "sites": 32
      },
      {
        "version": "3.2",
        "sites": 16
      }
    ]
  },
  {
    "version": "5.4",
    "sites": 495,
    "spip": [
      {
        "version": "1.9",
        "sites": 5
      },
      {
        "version": "2.0",
        "sites": 10
      },
      {
        "version": "2.1",
        "sites": 92
      },
      {
        "version": "3.0",
        "sites": 147
      },
      {
        "version": "3.1",
        "sites": 51
      },
      {
        "version": "3.2",
        "sites": 190
      }
    ]
  },
  {
    "version": "5.5",
    "sites": 85,
    "spip": [
      {
        "version": "1.9",
        "sites": 1
      },
      {
        "version": "2.1",
        "sites": 8
      },
      {
        "version": "3.0",
        "sites": 33
      },
      {
        "version": "3.1",
        "sites": 20
      },
      {
        "version": "3.2",
        "sites": 23
      }
    ]
  },
  {
    "version": "5.6",
    "sites": 1097,
    "spip": [
      {
        "version": "1.9",
        "sites": 5
      },
      {
        "version": "2.0",
        "sites": 16
      },
      {
        "version": "2.1",
        "sites": 44
      },
      {
        "version": "3.0",
        "sites": 427
      },
      {
        "version": "3.1",
        "sites": 291
      },
      {
        "version": "3.2",
        "sites": 313
      },
      {
        "version": "3.3",
        "sites": 1
      }
    ]
  },
  {
    "version": "7.0",
    "sites": 146,
    "spip": [
      {
        "version": "3.0",
        "sites": 1
      },
      {
        "version": "3.1",
        "sites": 43
      },
      {
        "version": "3.2",
        "sites": 100
      },
      {
        "version": "3.3",
        "sites": 2
      }
    ]
  },
  {
    "version": "7.1",
    "sites": 192,
    "spip": [
      {
        "version": "3.1",
        "sites": 24
      },
      {
        "version": "3.2",
        "sites": 167
      },
      {
        "version": "3.3",
        "sites": 1
      }
    ]
  },
  {
    "version": "7.2",
    "sites": 224,
    "spip": [
      {
        "version": "3.0",
        "sites": 1
      },
      {
        "version": "3.1",
        "sites": 15
      },
      {
        "version": "3.2",
        "sites": 202
      },
      {
        "version": "3.3",
        "sites": 6
      }
    ]
  },
  {
    "version": "7.3",
    "sites": 231,
    "spip": [
      {
        "version": "2.1",
        "sites": 2
      },
      {
        "version": "3.0",
        "sites": 1
      },
      {
        "version": "3.1",
        "sites": 36
      },
      {
        "version": "3.2",
        "sites": 180
      },
      {
        "version": "3.3",
        "sites": 12
      }
    ]
  },
  {
    "version": "7.4",
    "sites": 115,
    "spip": [
      {
        "version": "3.0",
        "sites": 2
      },
      {
        "version": "3.1",
        "sites": 7
      },
      {
        "version": "3.2",
        "sites": 100
      },
      {
        "version": "3.3",
        "sites": 6
      }
    ]
  }
]
