[
  {
    "version": "4.4",
    "sites": 1352,
    "spip": [
      {
        "version": "1.9",
        "sites": 338
      },
      {
        "version": "2.0",
        "sites": 444
      },
      {
        "version": "2.1",
        "sites": 570
      }
    ]
  },
  {
    "version": "5.1",
    "sites": 724,
    "spip": [
      {
        "version": "1.9",
        "sites": 29
      },
      {
        "version": "2.0",
        "sites": 71
      },
      {
        "version": "2.1",
        "sites": 236
      },
      {
        "version": "3.0",
        "sites": 383
      },
      {
        "version": "3.1",
        "sites": 5
      }
    ]
  },
  {
    "version": "5.2",
    "sites": 217,
    "spip": [
      {
        "version": "1.9",
        "sites": 21
      },
      {
        "version": "2.0",
        "sites": 23
      },
      {
        "version": "2.1",
        "sites": 85
      },
      {
        "version": "3.0",
        "sites": 71
      },
      {
        "version": "3.1",
        "sites": 17
      }
    ]
  },
  {
    "version": "5.3",
    "sites": 266,
    "spip": [
      {
        "version": "1.9",
        "sites": 19
      },
      {
        "version": "2.0",
        "sites": 11
      },
      {
        "version": "2.1",
        "sites": 65
      },
      {
        "version": "3.0",
        "sites": 112
      },
      {
        "version": "3.1",
        "sites": 42
      },
      {
        "version": "3.2",
        "sites": 17
      }
    ]
  },
  {
    "version": "5.4",
    "sites": 529,
    "spip": [
      {
        "version": "1.9",
        "sites": 5
      },
      {
        "version": "2.0",
        "sites": 11
      },
      {
        "version": "2.1",
        "sites": 97
      },
      {
        "version": "3.0",
        "sites": 163
      },
      {
        "version": "3.1",
        "sites": 55
      },
      {
        "version": "3.2",
        "sites": 198
      }
    ]
  },
  {
    "version": "5.5",
    "sites": 104,
    "spip": [
      {
        "version": "1.9",
        "sites": 2
      },
      {
        "version": "2.0",
        "sites": 1
      },
      {
        "version": "2.1",
        "sites": 11
      },
      {
        "version": "3.0",
        "sites": 40
      },
      {
        "version": "3.1",
        "sites": 24
      },
      {
        "version": "3.2",
        "sites": 26
      }
    ]
  },
  {
    "version": "5.6",
    "sites": 1169,
    "spip": [
      {
        "version": "1.9",
        "sites": 5
      },
      {
        "version": "2.0",
        "sites": 17
      },
      {
        "version": "2.1",
        "sites": 58
      },
      {
        "version": "3.0",
        "sites": 452
      },
      {
        "version": "3.1",
        "sites": 307
      },
      {
        "version": "3.2",
        "sites": 329
      },
      {
        "version": "3.3",
        "sites": 1
      }
    ]
  },
  {
    "version": "7.0",
    "sites": 171,
    "spip": [
      {
        "version": "3.0",
        "sites": 1
      },
      {
        "version": "3.1",
        "sites": 53
      },
      {
        "version": "3.2",
        "sites": 114
      },
      {
        "version": "3.3",
        "sites": 3
      }
    ]
  },
  {
    "version": "7.1",
    "sites": 196,
    "spip": [
      {
        "version": "3.1",
        "sites": 26
      },
      {
        "version": "3.2",
        "sites": 169
      },
      {
        "version": "3.3",
        "sites": 1
      }
    ]
  },
  {
    "version": "7.2",
    "sites": 331,
    "spip": [
      {
        "version": "2.1",
        "sites": 1
      },
      {
        "version": "3.0",
        "sites": 1
      },
      {
        "version": "3.1",
        "sites": 23
      },
      {
        "version": "3.2",
        "sites": 297
      },
      {
        "version": "3.3",
        "sites": 9
      }
    ]
  },
  {
    "version": "7.3",
    "sites": 389,
    "spip": [
      {
        "version": "2.1",
        "sites": 4
      },
      {
        "version": "3.0",
        "sites": 1
      },
      {
        "version": "3.1",
        "sites": 61
      },
      {
        "version": "3.2",
        "sites": 306
      },
      {
        "version": "3.3",
        "sites": 17
      }
    ]
  },
  {
    "version": "7.4",
    "sites": 97,
    "spip": [
      {
        "version": "2.1",
        "sites": 2
      },
      {
        "version": "3.0",
        "sites": 3
      },
      {
        "version": "3.1",
        "sites": 12
      },
      {
        "version": "3.2",
        "sites": 76
      },
      {
        "version": "3.3",
        "sites": 4
      }
    ]
  }
]
